[
  {
    "ApiId": "/providers/microsoft.powerapps/apis/shared_dynamicssmbsaas",
    "CdpRevision": {
      "BaseUrl": "/v3",
      "LastChangedTimeString": "2023-12-12T17:37:18.4720000Z",
      "RevisionNumber": 3
    },
    "ConnectedDataSourceInfoNameMapping": {
      "addressLine1": "Address Line 1",
      "addressLine2": "Address Line 2",
      "balance": "Balance",
      "blocked": "Blocked",
      "city": "City",
      "country": "Country/Region Code",
      "currencyCode": "Currency Code",
      "currencyId": "Currency Id",
      "displayName": "Display Name",
      "email": "Email",
      "id": "Id",
      "irs1099Code": "IRS1099 Code",
      "lastModifiedDateTime": "Last Modified Date",
      "number": "No.",
      "paymentMethodId": "Payment Method Id",
      "paymentTermsId": "Payment Terms Id",
      "phoneNumber": "Phone No.",
      "postalCode": "ZIP Code",
      "state": "State",
      "taxLiable": "Tax Liable",
      "taxRegistrationNumber": "Tax Registration No.",
      "website": "Website"
    },
    "DatasetName": "PRODUCTION-202303161607,071455fb-83f2-ed11-8848-002248f94e13",
    "EncodeDataset": true,
    "IsSampleData": false,
    "IsWritable": true,
    "Name": "vendors (v2.0)",
    "Type": "ConnectedDataSourceInfo"
  }
]